myCalculatorPackage_Jade_trial/__init__.py
myCalculatorPackage_Jade_trial/division/__init__.py
myCalculatorPackage_Jade_trial/division/divide.py
myCalculatorPackage_Jade_trial/multiplication/__init__.py
myCalculatorPackage_Jade_trial/multiplication/multiply.py
myCalculatorPackage_Jade_trial-0.0.2.dist-info/LICENSE.txt
myCalculatorPackage_Jade_trial-0.0.2.dist-info/METADATA
myCalculatorPackage_Jade_trial-0.0.2.dist-info/WHEEL
myCalculatorPackage_Jade_trial-0.0.2.dist-info/top_level.txt
myCalculatorPackage_Jade_trial-0.0.2.dist-info/RECORD
