Metadata-Version: 2.1
Name: myCalculatorPackage-Jade-trial
Version: 0.0.2
Summary: Change the name of example myCalculatorPackage
Author-email: Jade Yu <yujinxin01@gmail.com>
Project-URL: Homepage, https://github.com/khalad-hasan/myCalculatorPackage
Project-URL: Issues, https://github.com/khalad-hasan/myCalculatorPackage/issues
Classifier: Programming Language :: Python :: 3
Classifier: License :: OSI Approved :: MIT License
Classifier: Operating System :: OS Independent
Requires-Python: >=3.8
License-File: LICENSE.txt
